bzflag/__init__.py
bzflag/replay.py
bzflag/replay_duration.py
bzflag/replay_header.py
bzflag/networking/__init__.py
bzflag/networking/game_data.py
bzflag/networking/game_data_bzdb_setting.py
bzflag/networking/game_data_firing_info.py
bzflag/networking/game_data_flag.py
bzflag/networking/game_data_player.py
bzflag/networking/game_data_player_info.py
bzflag/networking/game_data_player_score.py
bzflag/networking/game_data_player_state.py
bzflag/networking/game_data_score.py
bzflag/networking/game_data_shot.py
bzflag/networking/game_data_team.py
bzflag/networking/game_packet.py
bzflag/networking/game_packet_mapping.py
bzflag/networking/msg_add_player.py
bzflag/networking/msg_admin_info.py
bzflag/networking/msg_alive.py
bzflag/networking/msg_capture_flag.py
bzflag/networking/msg_drop_flag.py
bzflag/networking/msg_flag_drop.py
bzflag/networking/msg_flag_grab.py
bzflag/networking/msg_flag_update.py
bzflag/networking/msg_game_time.py
bzflag/networking/msg_gm_update.py
bzflag/networking/msg_killed.py
bzflag/networking/msg_message.py
bzflag/networking/msg_new_rabbit.py
bzflag/networking/msg_null.py
bzflag/networking/msg_pause.py
bzflag/networking/msg_player_info.py
bzflag/networking/msg_player_update.py
bzflag/networking/msg_remove_player.py
bzflag/networking/msg_score.py
bzflag/networking/msg_score_over.py
bzflag/networking/msg_set_var.py
bzflag/networking/msg_shot_begin.py
bzflag/networking/msg_shot_end.py
bzflag/networking/msg_team_update.py
bzflag/networking/msg_teleport.py
bzflag/networking/msg_time_update.py
bzflag/networking/msg_transfer_flag.py
bzflag/networking/network_message.py
bzflag/networking/network_protocol.py
bzflag/networking/packet.py
bzflag/networking/packet_invalid_error.py
bzflag/networking/packet_not_set_error.py
bzflag/networking/unpackable.py
bzflag/utilities/__init__.py
bzflag/utilities/json_encoder.py
bzflag/utilities/json_serializable.py
bzflag_networking-1.0.2.dist-info/LICENSE.md
bzflag_networking-1.0.2.dist-info/METADATA
bzflag_networking-1.0.2.dist-info/WHEEL
bzflag_networking-1.0.2.dist-info/top_level.txt
bzflag_networking-1.0.2.dist-info/RECORD
