Metadata-Version: 2.1
Name: bzflag-networking
Version: 1.0.2
Summary: A Python library for reading and unpacking BZFlag network packets
Home-page: https://github.com/allejo/bzflag-networking.py
Author: Vladimir "allejo" Jimenez
Author-email: me@allejo.io
License: UNKNOWN
Platform: UNKNOWN
Classifier: License :: OSI Approved :: MIT License
Classifier: Programming Language :: Python :: 3
Classifier: Operating System :: OS Independent
